thl/__init__.py
thl/thl.py
thl-0.1.1.dist-info/METADATA
thl-0.1.1.dist-info/WHEEL
thl-0.1.1.dist-info/top_level.txt
thl-0.1.1.dist-info/RECORD
