Metadata-Version: 2.4
Name: thl
Version: 0.1.1
Summary: My Python package
Author: Jay
License: MIT
Requires-Python: >=3.8
